pallur/__init__.py
pallur/cli.py
pallur/command/__init__.py
pallur/command/configs.py
pallur/command/hosts.py
pallur/command/secret.py
pallur/exception/__init__.py
pallur/model/__init__.py
pallur/model/host.py
pallur/model/secret.py
pallur/model/task.py
pallur/module/__init__.py
pallur/module/config.py
pallur/module/database.py
pallur/module/encrypt.py
pallur/module/file_system.py
pallur/module/logger.py
pallur/module/output.py
pallur-0.1.1.dist-info/LICENSE.txt
pallur-0.1.1.dist-info/METADATA
pallur-0.1.1.dist-info/WHEEL
pallur-0.1.1.dist-info/entry_points.txt
pallur-0.1.1.dist-info/top_level.txt
pallur-0.1.1.dist-info/RECORD
