Metadata-Version: 2.1
Name: pallur
Version: 0.1.1
Summary: A Modern Command Line Tool for Apache Kafka.
Home-page: https://github.com/Clivern/Pallur/
Author: Clivern
Author-email: hello@clivern.com
License: MIT
Project-URL: Documentation, https://github.com/Clivern/Pallur/
Project-URL: Source, https://github.com/Clivern/Pallur/
Project-URL: Changelog, https://github.com/Clivern/Pallur/blob/main/CHANGELOG.rst
Project-URL: Tracker, https://github.com/Clivern/Pallur/issues
Project-URL: Download, https://pypi.org/project/Pallur/#files
Platform: any
Classifier: Development Status :: 5 - Production/Stable
Classifier: Programming Language :: Python
Classifier: License :: OSI Approved :: MIT License
License-File: LICENSE.txt
Requires-Dist: click (<=8.1.5)
Requires-Dist: PyYAML (<=6.0)
Requires-Dist: prettytable (<=3.8.0)
Requires-Dist: cryptography (<=41.0.2)
Requires-Dist: confluent-kafka (<=2.1.1)
Requires-Dist: importlib-metadata (<=6.8.0) ; python_version < "3.8"
